memegen/__init__.py
memegen/meme.py
tomassi_memegen-0.1.3.dist-info/METADATA
tomassi_memegen-0.1.3.dist-info/WHEEL
tomassi_memegen-0.1.3.dist-info/entry_points.txt
tomassi_memegen-0.1.3.dist-info/top_level.txt
tomassi_memegen-0.1.3.dist-info/RECORD
